parameteriser/__init__.py
parameteriser/_blast.py
parameteriser/_paths.py
parameteriser/_plot.py
parameteriser/_tex.py
parameteriser/_type_vars.py
parameteriser/_utils.py
parameteriser/py.typed
parameteriser/brenda/_v1/__init__.py
parameteriser/brenda/v0/__init__.py
parameteriser/experimental/__init__.py
parameteriser/experimental/deepmolecules.py
parameteriser-0.2.0.dist-info/METADATA
parameteriser-0.2.0.dist-info/WHEEL
parameteriser-0.2.0.dist-info/licenses/LICENSE
parameteriser-0.2.0.dist-info/RECORD
