Metadata-Version: 2.4
Name: parameteriser
Version: 0.2.0
Summary: Parameterisation of ODE models using the brenda database and AI tools
Project-URL: Changelog, https://gitlab.com/marvin.vanaalst/parameteriser/changelog.rst
Project-URL: Documentation, https://parameteriser.gitlab.io/mkdocs/
Project-URL: Homepage, https://gitlab.com/marvin.vanaalst/parameteriser
Project-URL: Issues, https://gitlab.com/marvin.vanaalst/parameteriser/-/issues
Project-URL: Repository, https://gitlab.com/marvin.vanaalst/parameteriser.git
Author-email: Marvin van Aalst <marvin.vanaalst@gmail.com>
License:                     GNU GENERAL PUBLIC LICENSE
License-File: LICENSE
Keywords: ai,enzyme,kinetics,machine learning
Classifier: Programming Language :: Python :: 3.11
Requires-Python: >=3.11
Requires-Dist: beautifulsoup4>=4.12.3
Requires-Dist: matplotlib>=3.10.0
Requires-Dist: more-itertools>=10.5.0
Requires-Dist: numpy>=2.0.0
Requires-Dist: pandas>=2.2.3
Requires-Dist: requests>=2.32.3
Requires-Dist: scipy>=1.14.1
Requires-Dist: selenium>=4.27.1
Requires-Dist: zeep>=4.3.1
Provides-Extra: dev
Requires-Dist: coverage>=7.6.4; extra == 'dev'
Requires-Dist: jupyter>=1.1.1; extra == 'dev'
Requires-Dist: mkdocs-jupyter>=0.25.1; extra == 'dev'
Requires-Dist: mkdocs-material>=9.5.42; extra == 'dev'
Requires-Dist: mkdocs>=1.6.1; extra == 'dev'
Requires-Dist: mypy>=1.13.0; extra == 'dev'
Requires-Dist: pre-commit>=4.0.1; extra == 'dev'
Requires-Dist: pyright>=1.1.387; extra == 'dev'
Requires-Dist: pytest-cov>=5.0.0; extra == 'dev'
Requires-Dist: pytest>=8.3.3; extra == 'dev'
Requires-Dist: qtbmodels<0.2,>=0.1.0; extra == 'dev'
Requires-Dist: ruff>=0.7.1; extra == 'dev'
Requires-Dist: ssort>=0.13.0; extra == 'dev'
Requires-Dist: toml-sort<0.24,>=0.23.1; extra == 'dev'
